visual_clutter/__init__.py
visual_clutter/clutter.py
visual_clutter/utils.py
visual_clutter-1.0.7.dist-info/LICENSE
visual_clutter-1.0.7.dist-info/METADATA
visual_clutter-1.0.7.dist-info/WHEEL
visual_clutter-1.0.7.dist-info/top_level.txt
visual_clutter-1.0.7.dist-info/RECORD
