Metadata-Version: 2.1
Name: visual-clutter
Version: 1.0.7
Summary: Python implementation of two measures of visual clutter (Feature Congestion and Subband Entropy)
Home-page: https://github.com/kargaranamir/visual-clutter
Author: Amir Hossein Kargaran
Author-email: kargaranamir@gmail.com
License: UNKNOWN
Project-URL: Bug Tracker, https://github.com/kargaranamir/visual-clutter/issues
Keywords: visual clutter,feature congestion,subband entropy
Platform: UNKNOWN
Classifier: Programming Language :: Python :: 3.6
Classifier: Programming Language :: Python :: 3.7
Classifier: Programming Language :: Python :: 3.8
Classifier: Programming Language :: Python :: 3.10
Classifier: License :: OSI Approved :: MIT License
Classifier: Operating System :: MacOS
Classifier: Operating System :: POSIX :: Linux
Requires-Python: >=3.6
Requires-Dist: opencv-python <4.6,>=4.5.3
Requires-Dist: numpy <1.25,>=1.22
Requires-Dist: scipy <1.10,>=1.7.0
Requires-Dist: Pillow <9.0,>=8.3.1
Requires-Dist: pyrtools <1.2.0,>=1.0.0
Requires-Dist: scikit-image <0.21,>=0.16.2
